README.rst
setup.cfg
setup.py
expirecache/__init__.py
expirecache.egg-info/PKG-INFO
expirecache.egg-info/SOURCES.txt
expirecache.egg-info/dependency_links.txt
expirecache.egg-info/top_level.txt