Metadata-Version: 1.1
Name: expirecache
Version: 1.0.0
Summary: A process-safe python adapter to handle cache expiration.
Home-page: https://github.com/kaelzhang/python-expire-cache
Author: Kael Zhang
Author-email: i@kael.me
License: MIT
Keywords: cache python expire memcached
Platform: UNKNOWN
Classifier: Programming Language :: Python
Classifier: Programming Language :: Python :: 2.6
Classifier: Programming Language :: Python :: 2.7
Classifier: Programming Language :: Python :: Implementation :: PyPy
Classifier: Topic :: Utilities
Classifier: License :: OSI Approved :: MIT License
